{
  "users": [
    {
      "id": 1,
      "firstName": "Madeline",
      "lastName": "Crowley",
      "email": "madeline@tunevids.com"
    }
  ],
  "savedVideos": [
    {
      "userId": 1,
      "title": "Unknown Mortal Orchestra - Boy Witch (FAN VIDEO)",
      "ytId": "btwm9UMYq1k",
      "ytChannelId": "UCal2BXtDTTHi9T4YDo4OoUg",
      "channelName": "BradSee",
      "duration": "PT2M25S",
      "timestamp": 1623863876198,
      "id": 2
    },
    {
      "userId": 1,
      "title": "Dinner - Siren Song (Official Video)",
      "ytId": "2LLKB4V13o8",
      "ytChannelId": "UC10Ot7i1OpwzlopW8Y6oQSQ",
      "channelName": "CapturedTracks",
      "duration": "PT3M33S",
      "timestamp": 1623863932783,
      "id": 4
    },
    {
      "userId": 1,
      "title": "Occhi dalle stelle (1978) Sherry Buchanan - Music by Marcello Giombini",
      "ytId": "SqBNXx_0l6g",
      "ytChannelId": "UCT2ftth8ztg3xbzPw_LVz3Q",
      "channelName": "davidfromlille",
      "duration": "PT1M29S",
      "timestamp": 1623866304113,
      "id": 5
    }
  ],
  "userChannels": [
    {
      "userId": 1,
      "title": "Cosmic Drop",
      "ytId": "UCB9vZ3lm2lOWBs-lSHTaRkQ",
      "uploadsId": "UUB9vZ3lm2lOWBs-lSHTaRkQ",
      "timestamp": 1624280315801,
      "id": 9
    },
    {
      "userId": 1,
      "title": "Vapor Memory",
      "ytId": "UCCCS8cRSiJjAqgwvmP7VxJw",
      "uploadsId": "UUCCS8cRSiJjAqgwvmP7VxJw",
      "timestamp": 1624280335275,
      "id": 10
    },
    {
      "userId": 1,
      "title": "Roxy Music",
      "ytId": "UCV4mMA9St1rYc4ANbve-KBA",
      "uploadsId": "UUV4mMA9St1rYc4ANbve-KBA",
      "timestamp": 1624280349125,
      "id": 11
    },
    {
      "userId": 1,
      "title": "PlasticPassions",
      "ytId": "UCoRpYZaQsSHA9oFgzcaGviQ",
      "uploadsId": "UUoRpYZaQsSHA9oFgzcaGviQ",
      "timestamp": 1624280385518,
      "id": 12
    },
    {
      "userId": 1,
      "title": "Epitaph Records",
      "ytId": "UCDE5Ezmxq1bNVak4lmkpCMw",
      "uploadsId": "UUDE5Ezmxq1bNVak4lmkpCMw",
      "timestamp": 1624280448270,
      "id": 13
    },
    {
      "userId": 1,
      "title": "MonsieurLunatique",
      "ytId": "UCxDw7lo0niULDPAoX1hGB2Q",
      "uploadsId": "UUxDw7lo0niULDPAoX1hGB2Q",
      "timestamp": 1624280477003,
      "id": 14
    },
    {
      "userId": 1,
      "title": "davidfromlille",
      "ytId": "UCT2ftth8ztg3xbzPw_LVz3Q",
      "uploadsId": "UUT2ftth8ztg3xbzPw_LVz3Q",
      "timestamp": 1624280493559,
      "id": 15
    }
  ],
  "playlists": [],
  "playlistVideos": []
}